jfibsem_dat/__init__.py
jfibsem_dat/calibrate.py
jfibsem_dat/cli.py
jfibsem_dat/read.py
jfibsem_dat/version.py
jfibsem_dat-0.2.0.dist-info/LICENSE
jfibsem_dat-0.2.0.dist-info/METADATA
jfibsem_dat-0.2.0.dist-info/WHEEL
jfibsem_dat-0.2.0.dist-info/entry_points.txt
jfibsem_dat-0.2.0.dist-info/top_level.txt
jfibsem_dat-0.2.0.dist-info/RECORD
