Metadata-Version: 2.1
Name: jfibsem-dat
Version: 0.2.0
Summary: UNKNOWN
Home-page: https://github.com/clbarnes/jfibsem_dat
Author: Chris L. Barnes
License: UNKNOWN
Platform: UNKNOWN
Classifier: Development Status :: 3 - Alpha
Classifier: License :: OSI Approved :: MIT License
Classifier: Programming Language :: Python :: 3
Classifier: Programming Language :: Python :: 3.8
Classifier: Programming Language :: Python :: 3.9
Classifier: Programming Language :: Python :: 3.10
Requires-Python: >=3.8, <4.0
License-File: LICENSE
Requires-Dist: numpy (>=1.22)
Requires-Dist: scipy
Provides-Extra: all
Requires-Dist: matplotlib ; extra == 'all'
Requires-Dist: matplotlib-scalebar ; extra == 'all'
Requires-Dist: scikit-image ; extra == 'all'
Provides-Extra: skimage
Requires-Dist: scikit-image ; extra == 'skimage'
Provides-Extra: vis
Requires-Dist: matplotlib ; extra == 'vis'
Requires-Dist: matplotlib-scalebar ; extra == 'vis'
